LibTextClassification-1.3.dist-info/METADATA
LibTextClassification-1.3.dist-info/RECORD
LibTextClassification-1.3.dist-info/WHEEL
LibTextClassification-1.3.dist-info/top_level.txt
data_util/__init__.py
data_util/data.py
data_util/preprocess_data.py
data_util/pretrain.py
model/__init__.py
model/averagePooling.py
model/predict.py
model/textCNN.py
model/textRNN.py
model/train.py
