Metadata-Version: 2.1
Name: LibTextClassification
Version: 1.3
Summary: Text Classification
Home-page: http://example.com/HelloWorld/
Author: Chong Wang
Author-email: 1147833662@qq.com
License: PSF
Keywords: Text Classification
Platform: UNKNOWN
Requires-Dist: bs4
Requires-Dist: gensim
Requires-Dist: nltk
Requires-Dist: numpy
Requires-Dist: tensorflow
Requires-Dist: tflearn
Requires-Dist: lxml
